[
  {
    "name": "PITHIE Laurence",
    "team": "Red Bull - BORA - hansgrohe (WT)",
    "age": 25,
    "tiers": {
      "sprint": "E",
      "itt": "E",
      "mountain": "E",
      "break_away": "E",
      "punch": "E"
    },
    "price": 0.5,
    "chance_of_abandon": 0.0
  },
  {
    "name": "VAN DIJKE Mick",
    "team": "Red Bull - BORA - hansgrohe (WT)",
    "age": 25,
    "tiers": {
      "sprint": "E",
      "itt": "E",
      "mountain": "E",
      "break_away": "E",
      "punch": "E"
    },
    "price": 0.5,
    "chance_of_abandon": 0.0
  },
  {
    "name": "MOSCON Gianni",
    "team": "Red Bull - BORA - hansgrohe (WT)",
    "age": 25,
    "tiers": {
      "sprint": "E",
      "itt": "E",
      "mountain": "E",
      "break_away": "E",
      "punch": "E"
    },
    "price": 0.5,
    "chance_of_abandon": 0.0
  },
  {
    "name": "MEEUS Jordi",
    "team": "Red Bull - BORA - hansgrohe (WT)",
    "age": 25,
    "tiers": {
      "sprint": "E",
      "itt": "E",
      "mountain": "E",
      "break_away": "E",
      "punch": "E"
    },
    "price": 0.5,
    "chance_of_abandon": 0.0
  },
  {
    "name": "BRAET Vito",
    "team": "Intermarch\u00e9 - Wanty (WT)",
    "age": 25,
    "tiers": {
      "sprint": "E",
      "itt": "E",
      "mountain": "E",
      "break_away": "E",
      "punch": "E"
    },
    "price": 0.5,
    "chance_of_abandon": 0.0
  },
  {
    "name": "RUTSCH Jonas",
    "team": "Intermarch\u00e9 - Wanty (WT)",
    "age": 25,
    "tiers": {
      "sprint": "E",
      "itt": "E",
      "mountain": "E",
      "break_away": "E",
      "punch": "E"
    },
    "price": 0.5,
    "chance_of_abandon": 0.0
  },
  {
    "name": "VAN SINTMAARTENSDIJK Roel",
    "team": "Intermarch\u00e9 - Wanty (WT)",
    "age": 25,
    "tiers": {
      "sprint": "E",
      "itt": "E",
      "mountain": "E",
      "break_away": "E",
      "punch": "E"
    },
    "price": 0.5,
    "chance_of_abandon": 0.0
  },
  {
    "name": "GRADEK Kamil",
    "team": "Bahrain - Victorious (WT)",
    "age": 25,
    "tiers": {
      "sprint": "E",
      "itt": "E",
      "mountain": "E",
      "break_away": "E",
      "punch": "E"
    },
    "price": 0.5,
    "chance_of_abandon": 0.0
  },
  {
    "name": "HAIG Jack",
    "team": "Bahrain - Victorious (WT)",
    "age": 25,
    "tiers": {
      "sprint": "E",
      "itt": "E",
      "mountain": "E",
      "break_away": "E",
      "punch": "E"
    },
    "price": 0.5,
    "chance_of_abandon": 0.0
  },
  {
    "name": "STANNARD Robert",
    "team": "Bahrain - Victorious (WT)",
    "age": 25,
    "tiers": {
      "sprint": "E",
      "itt": "E",
      "mountain": "E",
      "break_away": "E",
      "punch": "E"
    },
    "price": 0.5,
    "chance_of_abandon": 0.0
  },
  {
    "name": "WRIGHT Fred",
    "team": "Bahrain - Victorious (WT)",
    "age": 25,
    "tiers": {
      "sprint": "E",
      "itt": "E",
      "mountain": "E",
      "break_away": "E",
      "punch": "E"
    },
    "price": 0.5,
    "chance_of_abandon": 0.0
  },
  {
    "name": "BOIVIN Guillaume",
    "team": "Israel - Premier Tech (PRT)",
    "age": 25,
    "tiers": {
      "sprint": "E",
      "itt": "E",
      "mountain": "E",
      "break_away": "E",
      "punch": "E"
    },
    "price": 0.5,
    "chance_of_abandon": 0.0
  },
  {
    "name": "LOUVEL Matis",
    "team": "Israel - Premier Tech (PRT)",
    "age": 25,
    "tiers": {
      "sprint": "E",
      "itt": "E",
      "mountain": "E",
      "break_away": "E",
      "punch": "E"
    },
    "price": 0.5,
    "chance_of_abandon": 0.0
  },
  {
    "name": "NEILANDS Krists",
    "team": "Israel - Premier Tech (PRT)",
    "age": 25,
    "tiers": {
      "sprint": "E",
      "itt": "E",
      "mountain": "E",
      "break_away": "E",
      "punch": "E"
    },
    "price": 0.5,
    "chance_of_abandon": 0.0
  }
]